{
  "generator-jhipster": {
    "authenticationType": "jwt",
    "cacheProvider": "no",
    "serverPort": "8083",
    "serviceDiscoveryType": "eureka",
    "skipUserManagement": true,
    "baseName": "transaction",
    "buildTool": "gradle",
    "databaseType": "sql",
    "devDatabaseType": "h2Memory",
    "enableHibernateCache": false,
    "enableSwaggerCodegen": true,
    "enableTranslation": true,
    "jhiPrefix": "jhi",
    "languages": ["en", "nl", "ru"],
    "messageBroker": false,
    "nativeLanguage": "en",
    "prodDatabaseType": "postgresql",
    "searchEngine": false,
    "skipClient": true,
    "testFrameworks": [],
    "websocket": false,
    "reactive": false,
    "applicationType": "microservice",
    "packageName": "com.example.transaction",
    "packageFolder": "com/example/transaction",
    "clientPackageManager": "yarn",
    "uaaBaseName": "uaa",
    "jhipsterVersion": "6.10.3",
    "creationTimestamp": 1601861280225,
    "jwtSecretKey": "MDBjYTJkNWZiYTM3YjczYWYwNzk0ZmIxMTZhMzhhYzY3NWE5ODdjNmQ0ODkyMWVlOWVlMTBiYmVhNzk2Yzc4M2U5YmJlNmY3NzMyYjMxYTJjNTdlZjBlYzZlNTZjY2RmMjc4Y2U3M2ZiZmJiMjU5ZWY1MWFiNjFiN2RiMDJjZjk=",
    "embeddableLaunchScript": false,
    "entitySuffix": "",
    "dtoSuffix": "DTO",
    "otherModules": [],
    "blueprints": [],
    "prettierJava": true
  },
  "entities": ["MonetaryTransaction", "AccountState"]
}
